.gitignore
CHANGES.txt
CONTRIBUTORS.txt
COPYRIGHT.txt
LICENSE.txt
README.txt
TODO.txt
setup.cfg
setup.py
tox.ini
docs/Makefile
docs/api.rst
docs/changes.rst
docs/conf.py
docs/index.rst
docs/narr.rst
docs/.static/logo_hi.gif
repoze/__init__.py
repoze.evolution.egg-info/PKG-INFO
repoze.evolution.egg-info/SOURCES.txt
repoze.evolution.egg-info/dependency_links.txt
repoze.evolution.egg-info/entry_points.txt
repoze.evolution.egg-info/namespace_packages.txt
repoze.evolution.egg-info/not-zip-safe
repoze.evolution.egg-info/requires.txt
repoze.evolution.egg-info/top_level.txt
repoze/evolution/__init__.py
repoze/evolution/interfaces.py
repoze/evolution/tests/__init__.py
repoze/evolution/tests/test_evolution.py
repoze/evolution/tests/fixtureapp/__init__.py
repoze/evolution/tests/fixtureapp/evolve/__init__.py
repoze/evolution/tests/fixtureapp/evolve/evolve1.py
repoze/evolution/tests/fixtureapp/evolve/evolve2.py
repoze/evolution/tests/fixtureapp/evolve/evolve3.py